LICENSE
MANIFEST.in
README.rst
setup.py
crust/__init__.py
crust/api.py
crust/exceptions.py
crust/fields.py
crust/query.py
crust/requests.py
crust/resources.py
crust/six.py
crust/utils.py
crust.egg-info/PKG-INFO
crust.egg-info/SOURCES.txt
crust.egg-info/dependency_links.txt
crust.egg-info/not-zip-safe
crust.egg-info/requires.txt
crust.egg-info/top_level.txt