Metadata-Version: 1.0
Name: crust
Version: 0.1
Summary: Framework for Tastypie API Clients
Home-page: https://github.com/dstufft/crust/
Author: Donald Stufft
Author-email: donald.stufft@gmail.com
License: Copyright (c) Donald Stufft
